[
    {
        "id": 1,
        "name": "a",
        "sdt": "000211",
        "email": "",
        "diachi": "",
        "thanhpho": "giá rẻ bất ngờ",
        "quan":""
    },
    {
        "id": 2,
        "name": "b",
        "sdt": "000211",
        "email": "",
        "diachi": "",
        "thanhpho": "giá rẻ bất ngờ",
        "quan":""
    },
    {
         "id": 3,
        "name": "as",
        "sdt": "000211",
        "email": "",
        "diachi": "",
        "thanhpho": "giá rẻ bất ngờ",
        "quan":""
    },
    {
         "id": 4,
        "name": "ssssa",
        "sdt": "000211",
        "email": "",
        "diachi": "",
        "thanhpho": "giá rẻ bất ngờ",
        "quan":""
    },
    {
        "id": 5,
        "name": "aeff",
        "sdt": "000211",
        "email": "",
        "diachi": "",
        "thanhpho": "giá rẻ bất ngờ",
        "quan":""
    }
]